delibera/__init__.py
delibera/py.typed
delibera-0.1.0.dist-info/WHEEL
delibera-0.1.0.dist-info/METADATA
delibera-0.1.0.dist-info/RECORD
