Metadata-Version: 2.3
Name: delibera
Version: 0.1.0
Summary: An agentic application framework
Author: HuilinXu
Author-email: HuilinXu <huilinlynn@wustl.edu>
License:                                  Apache License
Classifier: Development Status :: 3 - Alpha
Classifier: Intended Audience :: Developers
Classifier: Programming Language :: Python :: 3
Classifier: Programming Language :: Python :: 3.12
Classifier: Programming Language :: Python :: 3.13
Requires-Python: >=3.12
Project-URL: Homepage, https://github.com/forge-labs-dev/delibera
Project-URL: Repository, https://github.com/forge-labs-dev/delibera
